{"GlobalPropertiesHash":"uBq19gXVLY4mKA+LB356npbEPvJGJXNAtCY+txfh4c4=","FingerprintPatternsHash":"gq3WsqcKBUGTSNle7RKKyXRIwh7M8ccEqOqYvIzoM04=","PropertyOverridesHash":"8ZRc1sGeVrPBx4lD717BgRaQekyh78QKV9SKsdt638U=","InputHashes":["aIXYQCtZWJjW2XV2Sw99YSa\u002BUlLKgSOyJnrHxHq11ds=","JhDE8bU7HguqWq4q4vXXMRpz2Zek1IDJ\u002BCPqlb9Sr30=","EASdJoUQ27ke77MPKY7PSom6/1VoVRxZdvF/KLXlNhY=","NU6/x3w2f2bArrToocudnyP/ynpClZsW4aAZbow9MqA=","Sa8m38KoibPBHVfz1kSl8VwT1b//ss32snp958sxzN4=","/bKq82YcvvzWwOdSOPbtqP\u002BoFxQTBj6lYDhfgOiptSY=","9r4kFR4IvN9XJigWvybK\u002BWsbpSy71jaQRvCplslZsKk=","3d3D\u002BtLPOE6sK9b8g4I0CnYybXjOt1PgcbQoiz9LPEY=","GZB456xrSk5HSkeezhYCu39LSGHRDt75dRUhVaQxbAI=","JlWUdZPal7Wd\u002BUah\u002B2WvIN7rfL27P77731LuLwSQKWc=","AbGOmXL3u2kz\u002BdaWbC37L\u002BHEIUZcEC6xUCmLT7FFnIs=","Uu3K21qgF7rCYece3Etzvu4LxKozDEv2AZ/AJOZYaGU=","xo/DlnHp3u4zUzfjFdS/pbV95ALgn18GYexFIOYeZm4=","r5/KOUC6Ka/igBUwVUH47uBfVv7xst/sxoU10v34r\u002Bo=","3RU2govkLHkLP3NzaHr/9PhnEPjJbRU\u002BJHhAkf3GGAA=","QTLUr5oiQrslzhy30ADDWwKrjdcuBi1nfvu4ttyPp\u002BQ=","0kQtf0tHcU4w/\u002BojOfOgC/3FConjSYou2vM2\u002B9pXmtY=","UQ\u002Bq4pvWvq5fDInhLxPCVVJdFJLX/Lhekj2Un9Hvx9w=","BG9HBdw4to5ewAwaP/2KkEwDlYjucT8V9V9tG\u002BpUBU4=","wpPZ9YzeejlPD5zHJ2cIyZy5YPYhinTJQLJVXnj66Ms=","bU6ohTqbof4Ke3VeDsyavSQjcmsDnpj2Q2zkv1R\u002BtX8=","fyEhxuRa6guazMotYxpAi0q/h1IAghV1CbiV2oovw8E=","83bAbWJjzCtqmki55hgS3qCMkDaRBFyWDiXC/gkdCn4=","DbvMu2CLALlVQ3iyu0dLLeYyFM\u002BF\u002BmlEVW5HTyGpe/I=","UFoO5GYQFBqxhUIBp6Ve44fRi\u002Bc4T1mBszMIJUXkP4c=","hfSsvQHx9RBHbFz3GzB1wFEflxeY8xwPCkHXccjAlUQ="],"CachedAssets":{"xo/DlnHp3u4zUzfjFdS/pbV95ALgn18GYexFIOYeZm4=":{"Identity":"C:\\Users\\subid\\source\\repos\\VibeQuestApp\\wwwroot\\favicon.ico","SourceId":"VibeQuestApp","SourceType":"Discovered","ContentRoot":"C:\\Users\\subid\\source\\repos\\VibeQuestApp\\wwwroot\\","BasePath":"_content/VibeQuestApp","RelativePath":"favicon#[.{fingerprint}]?.ico","AssetKind":"All","AssetMode":"All","AssetRole":"Primary","AssetMergeBehavior":null,"AssetMergeSource":"","RelatedAsset":null,"AssetTraitName":null,"AssetTraitValue":null,"Fingerprint":"61n19gt1b8","Integrity":"Jtxf9L\u002B5ITKRc1gIRl4VbUpGkRNfOBXjYTdhJD4facM=","CopyToOutputDirectory":"Never","CopyToPublishDirectory":"PreserveNewest","OriginalItemSpec":"wwwroot\\favicon.ico","FileLength":5430,"LastWriteTime":"2025-06-09T03:05:34.4962098+00:00"},"Uu3K21qgF7rCYece3Etzvu4LxKozDEv2AZ/AJOZYaGU=":{"Identity":"C:\\Users\\subid\\source\\repos\\VibeQuestApp\\wwwroot\\css\\site.css","SourceId":"VibeQuestApp","SourceType":"Discovered","ContentRoot":"C:\\Users\\subid\\source\\repos\\VibeQuestApp\\wwwroot\\","BasePath":"_content/VibeQuestApp","RelativePath":"css/site#[.{fingerprint}]?.css","AssetKind":"All","AssetMode":"All","AssetRole":"Primary","AssetMergeBehavior":null,"AssetMergeSource":"","RelatedAsset":null,"AssetTraitName":null,"AssetTraitValue":null,"Fingerprint":"1fpfb6x0uo","Integrity":"bQF09ZZOsk0T2q2MpSrJMbqdu0Ks9Ea03LFI7wJyLeU=","CopyToOutputDirectory":"Never","CopyToPublishDirectory":"PreserveNewest","OriginalItemSpec":"wwwroot\\css\\site.css","FileLength":2810,"LastWriteTime":"2025-06-09T03:05:34.393074+00:00"},"AbGOmXL3u2kz\u002BdaWbC37L\u002BHEIUZcEC6xUCmLT7FFnIs=":{"Identity":"C:\\Users\\subid\\source\\repos\\VibeQuestApp\\wwwroot\\css\\open-iconic\\README.md","SourceId":"VibeQuestApp","SourceType":"Discovered","ContentRoot":"C:\\Users\\subid\\source\\repos\\VibeQuestApp\\wwwroot\\","BasePath":"_content/VibeQuestApp","RelativePath":"css/open-iconic/README#[.{fingerprint}]?.md","AssetKind":"All","AssetMode":"All","AssetRole":"Primary","AssetMergeBehavior":null,"AssetMergeSource":"","RelatedAsset":null,"AssetTraitName":null,"AssetTraitValue":null,"Fingerprint":"8h4oiah9s0","Integrity":"rDb1fXbrDo8/dpt6Gi3UAobONVQv/lE2bB7lGwRQ0jM=","CopyToOutputDirectory":"Never","CopyToPublishDirectory":"PreserveNewest","OriginalItemSpec":"wwwroot\\css\\open-iconic\\README.md","FileLength":3658,"LastWriteTime":"2025-06-09T03:05:34.4992221+00:00"},"JlWUdZPal7Wd\u002BUah\u002B2WvIN7rfL27P77731LuLwSQKWc=":{"Identity":"C:\\Users\\subid\\source\\repos\\VibeQuestApp\\wwwroot\\css\\open-iconic\\ICON-LICENSE","SourceId":"VibeQuestApp","SourceType":"Discovered","ContentRoot":"C:\\Users\\subid\\source\\repos\\VibeQuestApp\\wwwroot\\","BasePath":"_content/VibeQuestApp","RelativePath":"css/open-iconic/ICON-LICENSE#[.{fingerprint}]?","AssetKind":"All","AssetMode":"All","AssetRole":"Primary","AssetMergeBehavior":null,"AssetMergeSource":"","RelatedAsset":null,"AssetTraitName":null,"AssetTraitValue":null,"Fingerprint":"4dwjve0o0b","Integrity":"aF5g/izareSj02F3MPSoTGNbcMBl9nmZKDe04zjU/ss=","CopyToOutputDirectory":"Never","CopyToPublishDirectory":"PreserveNewest","OriginalItemSpec":"wwwroot\\css\\open-iconic\\ICON-LICENSE","FileLength":1093,"LastWriteTime":"2025-06-09T03:05:34.498221+00:00"},"GZB456xrSk5HSkeezhYCu39LSGHRDt75dRUhVaQxbAI=":{"Identity":"C:\\Users\\subid\\source\\repos\\VibeQuestApp\\wwwroot\\css\\open-iconic\\font\\fonts\\open-iconic.woff","SourceId":"VibeQuestApp","SourceType":"Discovered","ContentRoot":"C:\\Users\\subid\\source\\repos\\VibeQuestApp\\wwwroot\\","BasePath":"_content/VibeQuestApp","RelativePath":"css/open-iconic/font/fonts/open-iconic#[.{fingerprint}]?.woff","AssetKind":"All","AssetMode":"All","AssetRole":"Primary","AssetMergeBehavior":null,"AssetMergeSource":"","RelatedAsset":null,"AssetTraitName":null,"AssetTraitValue":null,"Fingerprint":"h4d0pazwgy","Integrity":"cZPqVlRJfSNW0KaQ4\u002BUPOXZ/v/QzXlejRDwUNdZIofI=","CopyToOutputDirectory":"Never","CopyToPublishDirectory":"PreserveNewest","OriginalItemSpec":"wwwroot\\css\\open-iconic\\font\\fonts\\open-iconic.woff","FileLength":14984,"LastWriteTime":"2025-06-09T03:05:34.39711+00:00"},"3d3D\u002BtLPOE6sK9b8g4I0CnYybXjOt1PgcbQoiz9LPEY=":{"Identity":"C:\\Users\\subid\\source\\repos\\VibeQuestApp\\wwwroot\\css\\open-iconic\\font\\fonts\\open-iconic.ttf","SourceId":"VibeQuestApp","SourceType":"Discovered","ContentRoot":"C:\\Users\\subid\\source\\repos\\VibeQuestApp\\wwwroot\\","BasePath":"_content/VibeQuestApp","RelativePath":"css/open-iconic/font/fonts/open-iconic#[.{fingerprint}]?.ttf","AssetKind":"All","AssetMode":"All","AssetRole":"Primary","AssetMergeBehavior":null,"AssetMergeSource":"","RelatedAsset":null,"AssetTraitName":null,"AssetTraitValue":null,"Fingerprint":"ll5grcv8wv","Integrity":"p\u002BRP8CV3vRK1YbIkNzq3rPo1jyETPnR07ULb\u002BHVYL8w=","CopyToOutputDirectory":"Never","CopyToPublishDirectory":"PreserveNewest","OriginalItemSpec":"wwwroot\\css\\open-iconic\\font\\fonts\\open-iconic.ttf","FileLength":28028,"LastWriteTime":"2025-06-09T03:05:34.39711+00:00"},"9r4kFR4IvN9XJigWvybK\u002BWsbpSy71jaQRvCplslZsKk=":{"Identity":"C:\\Users\\subid\\source\\repos\\VibeQuestApp\\wwwroot\\css\\open-iconic\\font\\fonts\\open-iconic.svg","SourceId":"VibeQuestApp","SourceType":"Discovered","ContentRoot":"C:\\Users\\subid\\source\\repos\\VibeQuestApp\\wwwroot\\","BasePath":"_content/VibeQuestApp","RelativePath":"css/open-iconic/font/fonts/open-iconic#[.{fingerprint}]?.svg","AssetKind":"All","AssetMode":"All","AssetRole":"Primary","AssetMergeBehavior":null,"AssetMergeSource":"","RelatedAsset":null,"AssetTraitName":null,"AssetTraitValue":null,"Fingerprint":"sjnzgf7e1h","Integrity":"\u002BP1oQ5jPzOVJGC52E1oxGXIXxxCyMlqy6A9cNxGYzVk=","CopyToOutputDirectory":"Never","CopyToPublishDirectory":"PreserveNewest","OriginalItemSpec":"wwwroot\\css\\open-iconic\\font\\fonts\\open-iconic.svg","FileLength":55332,"LastWriteTime":"2025-06-09T03:05:34.3960972+00:00"},"/bKq82YcvvzWwOdSOPbtqP\u002BoFxQTBj6lYDhfgOiptSY=":{"Identity":"C:\\Users\\subid\\source\\repos\\VibeQuestApp\\wwwroot\\css\\open-iconic\\font\\fonts\\open-iconic.otf","SourceId":"VibeQuestApp","SourceType":"Discovered","ContentRoot":"C:\\Users\\subid\\source\\repos\\VibeQuestApp\\wwwroot\\","BasePath":"_content/VibeQuestApp","RelativePath":"css/open-iconic/font/fonts/open-iconic#[.{fingerprint}]?.otf","AssetKind":"All","AssetMode":"All","AssetRole":"Primary","AssetMergeBehavior":null,"AssetMergeSource":"","RelatedAsset":null,"AssetTraitName":null,"AssetTraitValue":null,"Fingerprint":"wk8x8xm0ah","Integrity":"sDUtuZAEzWZyv/U1xl/9D3ehyU69JE\u002BFvAcu5HQ\u002B/a0=","CopyToOutputDirectory":"Never","CopyToPublishDirectory":"PreserveNewest","OriginalItemSpec":"wwwroot\\css\\open-iconic\\font\\fonts\\open-iconic.otf","FileLength":20996,"LastWriteTime":"2025-06-09T03:05:34.3960972+00:00"},"Sa8m38KoibPBHVfz1kSl8VwT1b//ss32snp958sxzN4=":{"Identity":"C:\\Users\\subid\\source\\repos\\VibeQuestApp\\wwwroot\\css\\open-iconic\\font\\fonts\\open-iconic.eot","SourceId":"VibeQuestApp","SourceType":"Discovered","ContentRoot":"C:\\Users\\subid\\source\\repos\\VibeQuestApp\\wwwroot\\","BasePath":"_content/VibeQuestApp","RelativePath":"css/open-iconic/font/fonts/open-iconic#[.{fingerprint}]?.eot","AssetKind":"All","AssetMode":"All","AssetRole":"Primary","AssetMergeBehavior":null,"AssetMergeSource":"","RelatedAsset":null,"AssetTraitName":null,"AssetTraitValue":null,"Fingerprint":"0uw8dim9nl","Integrity":"OK3poGPgzKI2NzNgP07XMbJa3Dz6USoUh/chSkSvQpc=","CopyToOutputDirectory":"Never","CopyToPublishDirectory":"PreserveNewest","OriginalItemSpec":"wwwroot\\css\\open-iconic\\font\\fonts\\open-iconic.eot","FileLength":28196,"LastWriteTime":"2025-06-09T03:05:34.3955766+00:00"},"NU6/x3w2f2bArrToocudnyP/ynpClZsW4aAZbow9MqA=":{"Identity":"C:\\Users\\subid\\source\\repos\\VibeQuestApp\\wwwroot\\css\\open-iconic\\font\\css\\open-iconic-bootstrap.min.css","SourceId":"VibeQuestApp","SourceType":"Discovered","ContentRoot":"C:\\Users\\subid\\source\\repos\\VibeQuestApp\\wwwroot\\","BasePath":"_content/VibeQuestApp","RelativePath":"css/open-iconic/font/css/open-iconic-bootstrap.min#[.{fingerprint}]?.css","AssetKind":"All","AssetMode":"All","AssetRole":"Primary","AssetMergeBehavior":null,"AssetMergeSource":"","RelatedAsset":null,"AssetTraitName":null,"AssetTraitValue":null,"Fingerprint":"cmapd0fi15","Integrity":"BJ/G\u002Be\u002By7bQdrYkS2RBTyNfBHpA9IuGaPmf9htub5MQ=","CopyToOutputDirectory":"Never","CopyToPublishDirectory":"PreserveNewest","OriginalItemSpec":"wwwroot\\css\\open-iconic\\font\\css\\open-iconic-bootstrap.min.css","FileLength":9395,"LastWriteTime":"2025-06-09T03:05:34.3940741+00:00"},"EASdJoUQ27ke77MPKY7PSom6/1VoVRxZdvF/KLXlNhY=":{"Identity":"C:\\Users\\subid\\source\\repos\\VibeQuestApp\\wwwroot\\css\\open-iconic\\FONT-LICENSE","SourceId":"VibeQuestApp","SourceType":"Discovered","ContentRoot":"C:\\Users\\subid\\source\\repos\\VibeQuestApp\\wwwroot\\","BasePath":"_content/VibeQuestApp","RelativePath":"css/open-iconic/FONT-LICENSE#[.{fingerprint}]?","AssetKind":"All","AssetMode":"All","AssetRole":"Primary","AssetMergeBehavior":null,"AssetMergeSource":"","RelatedAsset":null,"AssetTraitName":null,"AssetTraitValue":null,"Fingerprint":"48tmkg660f","Integrity":"jA4J4h/k76zVxbFKEaWwFKJccmO0voOQ1DbUW\u002B5YNlI=","CopyToOutputDirectory":"Never","CopyToPublishDirectory":"PreserveNewest","OriginalItemSpec":"wwwroot\\css\\open-iconic\\FONT-LICENSE","FileLength":4103,"LastWriteTime":"2025-06-09T03:05:34.498221+00:00"},"JhDE8bU7HguqWq4q4vXXMRpz2Zek1IDJ\u002BCPqlb9Sr30=":{"Identity":"C:\\Users\\subid\\source\\repos\\VibeQuestApp\\wwwroot\\css\\bootstrap\\bootstrap.min.css.map","SourceId":"VibeQuestApp","SourceType":"Discovered","ContentRoot":"C:\\Users\\subid\\source\\repos\\VibeQuestApp\\wwwroot\\","BasePath":"_content/VibeQuestApp","RelativePath":"css/bootstrap/bootstrap.min.css#[.{fingerprint}]?.map","AssetKind":"All","AssetMode":"All","AssetRole":"Primary","AssetMergeBehavior":null,"AssetMergeSource":"","RelatedAsset":null,"AssetTraitName":null,"AssetTraitValue":null,"Fingerprint":"8inm30yfxf","Integrity":"gBwg2tmA0Ci2u54gMF1jNCVku6vznarkLS6D76htNNQ=","CopyToOutputDirectory":"Never","CopyToPublishDirectory":"PreserveNewest","OriginalItemSpec":"wwwroot\\css\\bootstrap\\bootstrap.min.css.map","FileLength":449111,"LastWriteTime":"2025-06-09T03:05:34.4972206+00:00"},"aIXYQCtZWJjW2XV2Sw99YSa\u002BUlLKgSOyJnrHxHq11ds=":{"Identity":"C:\\Users\\subid\\source\\repos\\VibeQuestApp\\wwwroot\\css\\bootstrap\\bootstrap.min.css","SourceId":"VibeQuestApp","SourceType":"Discovered","ContentRoot":"C:\\Users\\subid\\source\\repos\\VibeQuestApp\\wwwroot\\","BasePath":"_content/VibeQuestApp","RelativePath":"css/bootstrap/bootstrap.min#[.{fingerprint}]?.css","AssetKind":"All","AssetMode":"All","AssetRole":"Primary","AssetMergeBehavior":null,"AssetMergeSource":"","RelatedAsset":null,"AssetTraitName":null,"AssetTraitValue":null,"Fingerprint":"bpk8xqwxhs","Integrity":"z8OR40MowJ8GgK6P89Y\u002BhiJK5\u002BcclzFHzLhFQLL92bg=","CopyToOutputDirectory":"Never","CopyToPublishDirectory":"PreserveNewest","OriginalItemSpec":"wwwroot\\css\\bootstrap\\bootstrap.min.css","FileLength":162720,"LastWriteTime":"2025-06-09T03:05:34.4962098+00:00"}},"CachedCopyCandidates":{}}